{"cameraMode":{"drawMode":0,"name":"Shaded","section":"Shading Mode"},"sceneLighting":true,"audioPlay":false,"sceneViewState":{"showFog":true,"showMaterialUpdate":false,"showSkybox":true,"showFlares":true,"showImageEffects":true,"showParticleSystems":true},"in2DMode":false,"pivot":{"x":491.75750732421877,"y":550.8668823242188,"z":14.063232421875},"rotation":{"x":0.02068869210779667,"y":-0.003905197838321328,"z":-0.00008967515168478712,"w":-0.9998166561126709},"size":446.87945556640627,"orthographic":false}